{
    "key": "group_62b96cb779945",
    "title": "Post Details Page",
    "fields": [
        {
            "key": "field_62b96ce2c3b7d",
            "label": "Banner Section",
            "name": "",
            "type": "tab",
            "instructions": "",
            "required": 0,
            "conditional_logic": 0,
            "wrapper": {
                "width": "",
                "class": "",
                "id": ""
            },
            "placement": "left",
            "endpoint": 0
        },
        {
            "key": "field_62b96cf0c3b7e",
            "label": "Banner Image",
            "name": "banner_image",
            "type": "image",
            "instructions": "Required Image Size(1920 x 296)",
            "required": 0,
            "conditional_logic": 0,
            "wrapper": {
                "width": "",
                "class": "",
                "id": ""
            },
            "return_format": "array",
            "preview_size": "medium",
            "library": "all",
            "min_width": "",
            "min_height": "",
            "min_size": "",
            "max_width": "",
            "max_height": "",
            "max_size": "",
            "mime_types": ""
        },
        {
            "key": "field_62b96d1bc3b7f",
            "label": "Banner Title",
            "name": "banner_title",
            "type": "text",
            "instructions": "",
            "required": 0,
            "conditional_logic": 0,
            "wrapper": {
                "width": "",
                "class": "",
                "id": ""
            },
            "default_value": "",
            "placeholder": "",
            "prepend": "",
            "append": "",
            "maxlength": ""
        },
        {
            "key": "field_62b96d25c3b80",
            "label": "Banner Subtitle",
            "name": "banner_subtitle",
            "type": "text",
            "instructions": "",
            "required": 0,
            "conditional_logic": 0,
            "wrapper": {
                "width": "",
                "class": "",
                "id": ""
            },
            "default_value": "",
            "placeholder": "",
            "prepend": "",
            "append": "",
            "maxlength": ""
        },
        {
            "key": "field_62b96d31c3b81",
            "label": "Page Section",
            "name": "",
            "type": "tab",
            "instructions": "",
            "required": 0,
            "conditional_logic": 0,
            "wrapper": {
                "width": "",
                "class": "",
                "id": ""
            },
            "placement": "left",
            "endpoint": 0
        },
        {
            "key": "field_62b96d3dc3b82",
            "label": "Page Content",
            "name": "page_content",
            "type": "wysiwyg",
            "instructions": "",
            "required": 0,
            "conditional_logic": 0,
            "wrapper": {
                "width": "",
                "class": "",
                "id": ""
            },
            "default_value": "",
            "tabs": "all",
            "toolbar": "full",
            "media_upload": 1,
            "delay": 0
        },
        {
            "key": "field_62b96d5ec3b83",
            "label": "Page Bottom Content",
            "name": "page_bottom_content",
            "type": "wysiwyg",
            "instructions": "",
            "required": 0,
            "conditional_logic": 0,
            "wrapper": {
                "width": "",
                "class": "",
                "id": ""
            },
            "default_value": "",
            "tabs": "all",
            "toolbar": "full",
            "media_upload": 1,
            "delay": 0
        },
        {
            "key": "field_62b96d80c3b84",
            "label": "Sidebar Section",
            "name": "",
            "type": "tab",
            "instructions": "",
            "required": 0,
            "conditional_logic": 0,
            "wrapper": {
                "width": "",
                "class": "",
                "id": ""
            },
            "placement": "left",
            "endpoint": 0
        },
        {
            "key": "field_62c285cb77a85",
            "label": "Sidebar Ad Section?",
            "name": "sidebar_ad_section",
            "type": "true_false",
            "instructions": "",
            "required": 0,
            "conditional_logic": 0,
            "wrapper": {
                "width": "",
                "class": "",
                "id": ""
            },
            "message": "",
            "default_value": 0,
            "ui": 1,
            "ui_on_text": "Show",
            "ui_off_text": "Hide"
        },
        {
            "key": "field_62b96d98c3b85",
            "label": "Sidebar Ad Image",
            "name": "sidebar_ad_image",
            "type": "image",
            "instructions": "Required image size(304 x 167)",
            "required": 0,
            "conditional_logic": [
                [
                    {
                        "field": "field_62c285cb77a85",
                        "operator": "==",
                        "value": "1"
                    }
                ]
            ],
            "wrapper": {
                "width": "",
                "class": "",
                "id": ""
            },
            "return_format": "array",
            "preview_size": "medium",
            "library": "all",
            "min_width": "",
            "min_height": "",
            "min_size": "",
            "max_width": "",
            "max_height": "",
            "max_size": "",
            "mime_types": ""
        },
        {
            "key": "field_62b96de3c3b86",
            "label": "Sidebar Ad Title",
            "name": "sidebar_ad_title",
            "type": "text",
            "instructions": "",
            "required": 0,
            "conditional_logic": [
                [
                    {
                        "field": "field_62c285cb77a85",
                        "operator": "==",
                        "value": "1"
                    }
                ]
            ],
            "wrapper": {
                "width": "",
                "class": "",
                "id": ""
            },
            "default_value": "",
            "placeholder": "",
            "prepend": "",
            "append": "",
            "maxlength": ""
        },
        {
            "key": "field_62b96decc3b87",
            "label": "Sidebar Ad URL",
            "name": "sidebar_ad_url",
            "type": "url",
            "instructions": "",
            "required": 0,
            "conditional_logic": [
                [
                    {
                        "field": "field_62c285cb77a85",
                        "operator": "==",
                        "value": "1"
                    }
                ]
            ],
            "wrapper": {
                "width": "",
                "class": "",
                "id": ""
            },
            "default_value": "",
            "placeholder": ""
        },
        {
            "key": "field_62c2861577a86",
            "label": "Sidebar Contact Form Section?",
            "name": "sidebar_contact_form_section",
            "type": "true_false",
            "instructions": "",
            "required": 0,
            "conditional_logic": 0,
            "wrapper": {
                "width": "",
                "class": "",
                "id": ""
            },
            "message": "",
            "default_value": 0,
            "ui": 1,
            "ui_on_text": "Show",
            "ui_off_text": "Hide"
        },
        {
            "key": "field_62b96f64a8073",
            "label": "Sidebar Contact Form",
            "name": "sidebar_contact_form",
            "type": "relationship",
            "instructions": "",
            "required": 0,
            "conditional_logic": [
                [
                    {
                        "field": "field_62c2861577a86",
                        "operator": "==",
                        "value": "1"
                    }
                ]
            ],
            "wrapper": {
                "width": "",
                "class": "",
                "id": ""
            },
            "post_type": [
                "wpcf7_contact_form"
            ],
            "taxonomy": "",
            "filters": [
                "search"
            ],
            "elements": "",
            "min": "",
            "max": "",
            "return_format": "object"
        },
        {
            "key": "field_62c2864c77a88",
            "label": "Sidebar Course Section?",
            "name": "sidebar_course_section",
            "type": "true_false",
            "instructions": "",
            "required": 0,
            "conditional_logic": 0,
            "wrapper": {
                "width": "",
                "class": "",
                "id": ""
            },
            "message": "",
            "default_value": 0,
            "ui": 1,
            "ui_on_text": "Show",
            "ui_off_text": "Hide"
        },
        {
            "key": "field_62b96f7ba8074",
            "label": "Sidebar Course Product List",
            "name": "sidebar_course_product_list",
            "type": "relationship",
            "instructions": "",
            "required": 0,
            "conditional_logic": [
                [
                    {
                        "field": "field_62c2864c77a88",
                        "operator": "==",
                        "value": "1"
                    }
                ]
            ],
            "wrapper": {
                "width": "",
                "class": "",
                "id": ""
            },
            "post_type": [
                "product"
            ],
            "taxonomy": [
                "product_cat:courses"
            ],
            "filters": [
                "search"
            ],
            "elements": "",
            "min": "",
            "max": "",
            "return_format": "object"
        },
        {
            "key": "field_62cfbf8c7bf0e",
            "label": "Sidebar Course List",
            "name": "sidebar_course_list",
            "type": "relationship",
            "instructions": "",
            "required": 0,
            "conditional_logic": [
                [
                    {
                        "field": "field_62c2864c77a88",
                        "operator": "==",
                        "value": "1"
                    }
                ]
            ],
            "wrapper": {
                "width": "",
                "class": "",
                "id": ""
            },
            "post_type": [
                "courses"
            ],
            "taxonomy": "",
            "filters": [
                "search"
            ],
            "elements": "",
            "min": "",
            "max": "",
            "return_format": "object"
        },
        {
            "key": "field_62beba8afe48a",
            "label": "Good to Know Section",
            "name": "",
            "type": "tab",
            "instructions": "",
            "required": 0,
            "conditional_logic": 0,
            "wrapper": {
                "width": "",
                "class": "",
                "id": ""
            },
            "placement": "left",
            "endpoint": 0
        },
        {
            "key": "field_62bebaa3fe48b",
            "label": "Good to Know Title",
            "name": "good_to_know_title",
            "type": "text",
            "instructions": "",
            "required": 0,
            "conditional_logic": 0,
            "wrapper": {
                "width": "",
                "class": "",
                "id": ""
            },
            "default_value": "",
            "placeholder": "",
            "prepend": "",
            "append": "",
            "maxlength": ""
        },
        {
            "key": "field_62bebaaffe48c",
            "label": "Good to Know Content",
            "name": "good_to_know_content",
            "type": "wysiwyg",
            "instructions": "",
            "required": 0,
            "conditional_logic": 0,
            "wrapper": {
                "width": "",
                "class": "",
                "id": ""
            },
            "default_value": "",
            "tabs": "all",
            "toolbar": "full",
            "media_upload": 1,
            "delay": 0
        },
        {
            "key": "field_62c6df2e643b8",
            "label": "Reading",
            "name": "",
            "type": "tab",
            "instructions": "",
            "required": 0,
            "conditional_logic": 0,
            "wrapper": {
                "width": "",
                "class": "",
                "id": ""
            },
            "placement": "left",
            "endpoint": 0
        },
        {
            "key": "field_62c6dea180ad9",
            "label": "Show Reading",
            "name": "show_reading",
            "type": "true_false",
            "instructions": "",
            "required": 0,
            "conditional_logic": 0,
            "wrapper": {
                "width": "",
                "class": "",
                "id": ""
            },
            "message": "",
            "default_value": 0,
            "ui": 1,
            "ui_on_text": "Show",
            "ui_off_text": "Hide"
        },
        {
            "key": "field_62c6df62a14a0",
            "label": "Our Courses Title",
            "name": "our_courses_title",
            "type": "wysiwyg",
            "instructions": "",
            "required": 0,
            "conditional_logic": 0,
            "wrapper": {
                "width": "",
                "class": "",
                "id": ""
            },
            "default_value": "",
            "tabs": "all",
            "toolbar": "full",
            "media_upload": 1,
            "delay": 0
        },
        {
            "key": "field_62c6df6ea14a1",
            "label": "Our Courses",
            "name": "our_courses",
            "type": "repeater",
            "instructions": "",
            "required": 0,
            "conditional_logic": 0,
            "wrapper": {
                "width": "",
                "class": "",
                "id": ""
            },
            "collapsed": "",
            "min": 0,
            "max": 0,
            "layout": "table",
            "button_label": "",
            "sub_fields": [
                {
                    "key": "field_62c6df7ba14a2",
                    "label": "Courses Image",
                    "name": "courses_image",
                    "type": "image",
                    "instructions": "Upload Image Size 433 × 238 px",
                    "required": 0,
                    "conditional_logic": 0,
                    "wrapper": {
                        "width": "",
                        "class": "",
                        "id": ""
                    },
                    "return_format": "array",
                    "preview_size": "medium",
                    "library": "all",
                    "min_width": "",
                    "min_height": "",
                    "min_size": "",
                    "max_width": "",
                    "max_height": "",
                    "max_size": "",
                    "mime_types": ""
                },
                {
                    "key": "field_62c6df90a14a3",
                    "label": "Courses Title",
                    "name": "courses_title",
                    "type": "link",
                    "instructions": "",
                    "required": 0,
                    "conditional_logic": 0,
                    "wrapper": {
                        "width": "",
                        "class": "",
                        "id": ""
                    },
                    "return_format": "array"
                }
            ]
        },
        {
            "key": "field_62b96f91a8075",
            "label": "Advance Section",
            "name": "",
            "type": "tab",
            "instructions": "",
            "required": 0,
            "conditional_logic": 0,
            "wrapper": {
                "width": "",
                "class": "",
                "id": ""
            },
            "placement": "left",
            "endpoint": 0
        },
        {
            "key": "field_62b96fc4a8077",
            "label": "Our Courses Section?",
            "name": "our_courses_section",
            "type": "true_false",
            "instructions": "",
            "required": 0,
            "conditional_logic": 0,
            "wrapper": {
                "width": "",
                "class": "",
                "id": ""
            },
            "message": "",
            "default_value": 0,
            "ui": 1,
            "ui_on_text": "Show",
            "ui_off_text": "Hide"
        },
        {
            "key": "field_62b96ff2a8078",
            "label": "Address Section?",
            "name": "address_section",
            "type": "true_false",
            "instructions": "",
            "required": 0,
            "conditional_logic": 0,
            "wrapper": {
                "width": "",
                "class": "",
                "id": ""
            },
            "message": "",
            "default_value": 0,
            "ui": 1,
            "ui_on_text": "Show",
            "ui_off_text": "Hide"
        }
    ],
    "location": [
        [
            {
                "param": "page_template",
                "operator": "==",
                "value": "page-templates\/post-details-page.php"
            }
        ]
    ],
    "menu_order": 0,
    "position": "normal",
    "style": "default",
    "label_placement": "top",
    "instruction_placement": "label",
    "hide_on_screen": [
        "the_content",
        "excerpt",
        "discussion"
    ],
    "active": true,
    "description": "",
    "show_in_rest": 0,
    "modified": 1657782194
}