{
    "key": "group_62b436bd02ab2",
    "title": "Courses Page",
    "fields": [
        {
            "key": "field_62b43958f6260",
            "label": "Banner Section",
            "name": "",
            "type": "tab",
            "instructions": "",
            "required": 0,
            "conditional_logic": 0,
            "wrapper": {
                "width": "",
                "class": "",
                "id": ""
            },
            "placement": "left",
            "endpoint": 0
        },
        {
            "key": "field_62b43988f6261",
            "label": "Banner Image",
            "name": "banner_image",
            "type": "image",
            "instructions": "Required Image Size(1920 x 296)",
            "required": 0,
            "conditional_logic": 0,
            "wrapper": {
                "width": "",
                "class": "",
                "id": ""
            },
            "return_format": "array",
            "preview_size": "medium",
            "library": "all",
            "min_width": "",
            "min_height": "",
            "min_size": "",
            "max_width": "",
            "max_height": "",
            "max_size": "",
            "mime_types": ""
        },
        {
            "key": "field_62b43995f6262",
            "label": "Banner Title",
            "name": "banner_title",
            "type": "text",
            "instructions": "",
            "required": 0,
            "conditional_logic": 0,
            "wrapper": {
                "width": "",
                "class": "",
                "id": ""
            },
            "default_value": "",
            "placeholder": "",
            "prepend": "",
            "append": "",
            "maxlength": ""
        },
        {
            "key": "field_62b4399bf6263",
            "label": "Banner Sub Title",
            "name": "banner_sub_title",
            "type": "text",
            "instructions": "",
            "required": 0,
            "conditional_logic": 0,
            "wrapper": {
                "width": "",
                "class": "",
                "id": ""
            },
            "default_value": "",
            "placeholder": "",
            "prepend": "",
            "append": "",
            "maxlength": ""
        },
        {
            "key": "field_62b439f4f6264",
            "label": "Courses Section",
            "name": "",
            "type": "tab",
            "instructions": "",
            "required": 0,
            "conditional_logic": 0,
            "wrapper": {
                "width": "",
                "class": "",
                "id": ""
            },
            "placement": "left",
            "endpoint": 0
        },
        {
            "key": "field_62b43a0bf6265",
            "label": "Courses Title",
            "name": "courses_title",
            "type": "text",
            "instructions": "",
            "required": 0,
            "conditional_logic": 0,
            "wrapper": {
                "width": "",
                "class": "",
                "id": ""
            },
            "default_value": "",
            "placeholder": "",
            "prepend": "",
            "append": "",
            "maxlength": ""
        },
        {
            "key": "field_62b43a22f6266",
            "label": "Courses Content",
            "name": "courses_content",
            "type": "wysiwyg",
            "instructions": "",
            "required": 0,
            "conditional_logic": 0,
            "wrapper": {
                "width": "",
                "class": "",
                "id": ""
            },
            "default_value": "",
            "tabs": "all",
            "toolbar": "full",
            "media_upload": 1,
            "delay": 0
        },
        {
            "key": "field_62b43a33f6267",
            "label": "Courses List",
            "name": "courses_list",
            "type": "relationship",
            "instructions": "",
            "required": 0,
            "conditional_logic": 0,
            "wrapper": {
                "width": "",
                "class": "",
                "id": ""
            },
            "post_type": [
                "courses"
            ],
            "taxonomy": "",
            "filters": [
                "search"
            ],
            "elements": "",
            "min": "",
            "max": "",
            "return_format": "object"
        },
        {
            "key": "field_62b43a4ff6268",
            "label": "Products Section",
            "name": "",
            "type": "tab",
            "instructions": "",
            "required": 0,
            "conditional_logic": 0,
            "wrapper": {
                "width": "",
                "class": "",
                "id": ""
            },
            "placement": "left",
            "endpoint": 0
        },
        {
            "key": "field_62bd38f2c8be0",
            "label": "Show Course Products Section?",
            "name": "show_course_products_section",
            "type": "true_false",
            "instructions": "",
            "required": 0,
            "conditional_logic": 0,
            "wrapper": {
                "width": "",
                "class": "",
                "id": ""
            },
            "message": "",
            "default_value": 0,
            "ui": 1,
            "ui_on_text": "",
            "ui_off_text": ""
        },
        {
            "key": "field_62b43a63f6269",
            "label": "Product Title",
            "name": "product_title",
            "type": "text",
            "instructions": "",
            "required": 0,
            "conditional_logic": [
                [
                    {
                        "field": "field_62bd38f2c8be0",
                        "operator": "==",
                        "value": "1"
                    }
                ]
            ],
            "wrapper": {
                "width": "",
                "class": "",
                "id": ""
            },
            "default_value": "",
            "placeholder": "",
            "prepend": "",
            "append": "",
            "maxlength": ""
        },
        {
            "key": "field_62b43a6cf626a",
            "label": "Product Content",
            "name": "product_content",
            "type": "wysiwyg",
            "instructions": "",
            "required": 0,
            "conditional_logic": [
                [
                    {
                        "field": "field_62bd38f2c8be0",
                        "operator": "==",
                        "value": "1"
                    }
                ]
            ],
            "wrapper": {
                "width": "",
                "class": "",
                "id": ""
            },
            "default_value": "",
            "tabs": "all",
            "toolbar": "full",
            "media_upload": 1,
            "delay": 0
        },
        {
            "key": "field_62b43a7bf626b",
            "label": "Product List",
            "name": "product_list",
            "type": "relationship",
            "instructions": "",
            "required": 0,
            "conditional_logic": [
                [
                    {
                        "field": "field_62bd38f2c8be0",
                        "operator": "==",
                        "value": "1"
                    }
                ]
            ],
            "wrapper": {
                "width": "",
                "class": "",
                "id": ""
            },
            "post_type": [
                "product"
            ],
            "taxonomy": [
                "product_cat:courses"
            ],
            "filters": [
                "search"
            ],
            "elements": "",
            "min": "",
            "max": "",
            "return_format": "object"
        },
        {
            "key": "field_62b43a9af626c",
            "label": "Offering Section",
            "name": "",
            "type": "tab",
            "instructions": "",
            "required": 0,
            "conditional_logic": [
                [
                    {
                        "field": "field_62bd38f2c8be0",
                        "operator": "==",
                        "value": "1"
                    }
                ]
            ],
            "wrapper": {
                "width": "",
                "class": "",
                "id": ""
            },
            "placement": "left",
            "endpoint": 0
        },
        {
            "key": "field_62b43abef626d",
            "label": "Offering Title",
            "name": "offering_title",
            "type": "wysiwyg",
            "instructions": "",
            "required": 0,
            "conditional_logic": [
                [
                    {
                        "field": "field_62bd38f2c8be0",
                        "operator": "==",
                        "value": "1"
                    }
                ]
            ],
            "wrapper": {
                "width": "",
                "class": "",
                "id": ""
            },
            "default_value": "",
            "tabs": "all",
            "toolbar": "full",
            "media_upload": 1,
            "delay": 0
        },
        {
            "key": "field_62b43ac8f626e",
            "label": "Offering Content",
            "name": "offering_content",
            "type": "wysiwyg",
            "instructions": "",
            "required": 0,
            "conditional_logic": [
                [
                    {
                        "field": "field_62bd38f2c8be0",
                        "operator": "==",
                        "value": "1"
                    }
                ]
            ],
            "wrapper": {
                "width": "",
                "class": "",
                "id": ""
            },
            "default_value": "",
            "tabs": "all",
            "toolbar": "full",
            "media_upload": 1,
            "delay": 0
        },
        {
            "key": "field_62b43ad0f626f",
            "label": "Offering Image",
            "name": "offering_image",
            "type": "image",
            "instructions": "Required Image Size(580 x 510)",
            "required": 0,
            "conditional_logic": [
                [
                    {
                        "field": "field_62bd38f2c8be0",
                        "operator": "==",
                        "value": "1"
                    }
                ]
            ],
            "wrapper": {
                "width": "",
                "class": "",
                "id": ""
            },
            "return_format": "array",
            "preview_size": "medium",
            "library": "all",
            "min_width": "",
            "min_height": "",
            "min_size": "",
            "max_width": "",
            "max_height": "",
            "max_size": "",
            "mime_types": ""
        },
        {
            "key": "field_62bebe012d36a",
            "label": "Responsible Section",
            "name": "",
            "type": "tab",
            "instructions": "",
            "required": 0,
            "conditional_logic": 0,
            "wrapper": {
                "width": "",
                "class": "",
                "id": ""
            },
            "placement": "left",
            "endpoint": 0
        },
        {
            "key": "field_62bebe122d36b",
            "label": "Responsible Title",
            "name": "responsible_title",
            "type": "text",
            "instructions": "",
            "required": 0,
            "conditional_logic": 0,
            "wrapper": {
                "width": "",
                "class": "",
                "id": ""
            },
            "default_value": "",
            "placeholder": "",
            "prepend": "",
            "append": "",
            "maxlength": ""
        },
        {
            "key": "field_62bebe212d36c",
            "label": "Responsible Content",
            "name": "responsible_content",
            "type": "wysiwyg",
            "instructions": "",
            "required": 0,
            "conditional_logic": 0,
            "wrapper": {
                "width": "",
                "class": "",
                "id": ""
            },
            "default_value": "",
            "tabs": "all",
            "toolbar": "full",
            "media_upload": 1,
            "delay": 0
        },
        {
            "key": "field_62c6e2c9d2787",
            "label": "Reading",
            "name": "",
            "type": "tab",
            "instructions": "",
            "required": 0,
            "conditional_logic": 0,
            "wrapper": {
                "width": "",
                "class": "",
                "id": ""
            },
            "placement": "left",
            "endpoint": 0
        },
        {
            "key": "field_62c6e2dbd2788",
            "label": "Show Reading",
            "name": "show_reading",
            "type": "true_false",
            "instructions": "",
            "required": 0,
            "conditional_logic": 0,
            "wrapper": {
                "width": "",
                "class": "",
                "id": ""
            },
            "message": "",
            "default_value": 0,
            "ui": 1,
            "ui_on_text": "Show",
            "ui_off_text": "Hide"
        },
        {
            "key": "field_62c6e2ead2789",
            "label": "Our Courses Title",
            "name": "our_courses_title",
            "type": "wysiwyg",
            "instructions": "",
            "required": 0,
            "conditional_logic": 0,
            "wrapper": {
                "width": "",
                "class": "",
                "id": ""
            },
            "default_value": "",
            "tabs": "all",
            "toolbar": "full",
            "media_upload": 1,
            "delay": 0
        },
        {
            "key": "field_62c6e303d278a",
            "label": "Our Courses",
            "name": "our_courses",
            "type": "repeater",
            "instructions": "",
            "required": 0,
            "conditional_logic": 0,
            "wrapper": {
                "width": "",
                "class": "",
                "id": ""
            },
            "collapsed": "",
            "min": 0,
            "max": 0,
            "layout": "table",
            "button_label": "",
            "sub_fields": [
                {
                    "key": "field_62c6e320d278b",
                    "label": "Courses Image",
                    "name": "courses_image",
                    "type": "image",
                    "instructions": "Upload Image Size 433 × 238 px",
                    "required": 0,
                    "conditional_logic": 0,
                    "wrapper": {
                        "width": "",
                        "class": "",
                        "id": ""
                    },
                    "return_format": "array",
                    "preview_size": "medium",
                    "library": "all",
                    "min_width": "",
                    "min_height": "",
                    "min_size": "",
                    "max_width": "",
                    "max_height": "",
                    "max_size": "",
                    "mime_types": ""
                },
                {
                    "key": "field_62c6e335d278c",
                    "label": "Courses Title",
                    "name": "courses_title",
                    "type": "link",
                    "instructions": "",
                    "required": 0,
                    "conditional_logic": 0,
                    "wrapper": {
                        "width": "",
                        "class": "",
                        "id": ""
                    },
                    "return_format": "array"
                }
            ]
        },
        {
            "key": "field_62b4661c10156",
            "label": "Advance Section",
            "name": "",
            "type": "tab",
            "instructions": "",
            "required": 0,
            "conditional_logic": 0,
            "wrapper": {
                "width": "",
                "class": "",
                "id": ""
            },
            "placement": "left",
            "endpoint": 0
        },
        {
            "key": "field_62b466f30182e",
            "label": "Location Section?",
            "name": "location_section",
            "type": "true_false",
            "instructions": "",
            "required": 0,
            "conditional_logic": 0,
            "wrapper": {
                "width": "",
                "class": "",
                "id": ""
            },
            "message": "",
            "default_value": 0,
            "ui": 1,
            "ui_on_text": "Show",
            "ui_off_text": "Hide"
        }
    ],
    "location": [
        [
            {
                "param": "page_template",
                "operator": "==",
                "value": "page-templates\/courses-page.php"
            }
        ]
    ],
    "menu_order": 0,
    "position": "normal",
    "style": "default",
    "label_placement": "top",
    "instruction_placement": "label",
    "hide_on_screen": [
        "the_content",
        "excerpt",
        "discussion",
        "comments"
    ],
    "active": true,
    "description": "",
    "show_in_rest": 0,
    "modified": 1657201999
}